SmartJsonPy/__init__.py
SmartJsonPy/cleaner.py
SmartJsonPy/extractor.py
SmartJsonPy/transformer.py
SmartJsonPy/utils.py
SmartJsonPy/validator.py
smartjsonpy-1.1.0.dist-info/licenses/LICENSE
tests/__init__.py
tests/test_cleaner.py
tests/test_extractor.py
tests/test_transformer.py
tests/test_utils.py
tests/test_validator.py
smartjsonpy-1.1.0.dist-info/METADATA
smartjsonpy-1.1.0.dist-info/WHEEL
smartjsonpy-1.1.0.dist-info/top_level.txt
smartjsonpy-1.1.0.dist-info/RECORD
