Metadata-Version: 2.4
Name: SmartJsonPy
Version: 1.1.0
Summary: Funções inteligentes para validação, limpeza e conversão de JSON em Python
Author: Roberto Lima
Author-email: Roberto Lima <robertolima.izphera@gmail.com>
License: MIT
Project-URL: Homepage, https://github.com/robertolima-dev/SmartJsonPy
Project-URL: Repository, https://github.com/robertolima-dev/SmartJsonPy
Project-URL: Documentation, https://pypi.org/project/SmartJsonPy/
Keywords: json,validação,limpeza,parser,conversão,utils,python
Classifier: Programming Language :: Python :: 3
Classifier: License :: OSI Approved :: MIT License
Classifier: Operating System :: OS Independent
Requires-Python: >=3.7
License-File: LICENSE
Requires-Dist: pyyaml>=6.0
Requires-Dist: xmltodict>=0.13.0
Requires-Dist: pandas>=2.0.0
Dynamic: author
Dynamic: license-file
Dynamic: requires-python
